dxfgrabber/__init__.py
dxfgrabber/acdsdata.py
dxfgrabber/blockssection.py
dxfgrabber/codepage.py
dxfgrabber/color.py
dxfgrabber/const.py
dxfgrabber/decode.py
dxfgrabber/defaultchunk.py
dxfgrabber/drawing.py
dxfgrabber/dxfentities.py
dxfgrabber/dxfobjects.py
dxfgrabber/entitysection.py
dxfgrabber/headersection.py
dxfgrabber/juliandate.py
dxfgrabber/layers.py
dxfgrabber/linetypes.py
dxfgrabber/sections.py
dxfgrabber/styles.py
dxfgrabber/tablessection.py
dxfgrabber/tags.py
dxfgrabber-1.0.0.dist-info/DESCRIPTION.rst
dxfgrabber-1.0.0.dist-info/METADATA
dxfgrabber-1.0.0.dist-info/RECORD
dxfgrabber-1.0.0.dist-info/WHEEL
dxfgrabber-1.0.0.dist-info/metadata.json
dxfgrabber-1.0.0.dist-info/top_level.txt
