Metadata-Version: 1.1
Name: dxfgrabber
Version: 1.0.0
Summary: A Python library to grab information from DXF drawings - all DXF versions supported.
Home-page: https://github.com/mozman/dxfgrabber.git
Author: Manfred Moitzi
Author-email: mozman@gmx.at
License: MIT License
Download-URL: https://github.com/mozman/dxfgrabber/releases
Keywords: DXF,CAD
Platform: OS Independent
Classifier: Development Status :: 5 - Production/Stable
Classifier: License :: OSI Approved :: MIT License
Classifier: Operating System :: OS Independent
Classifier: Programming Language :: Python :: 2.7
Classifier: Programming Language :: Python :: 3
Classifier: Programming Language :: Python :: 3.6
Classifier: Programming Language :: Python :: Implementation :: CPython
Classifier: Programming Language :: Python :: Implementation :: PyPy
Classifier: Intended Audience :: Developers
Classifier: Topic :: Software Development :: Libraries :: Python Modules
Provides: dxfgrabber
